Bullseye/Bullseye.py
Bullseye/__init__.py
Bullseye/__main__.py
Bullseye/config.py
Bullseye/discord.py
Bullseye/keyring.py
Bullseye/messages.py
Bullseye/user_agent_data.py
Bullseye/user_agents.py
Bullseye_DC-0.1.0.dist-info/LICENSE
Bullseye_DC-0.1.0.dist-info/METADATA
Bullseye_DC-0.1.0.dist-info/WHEEL
Bullseye_DC-0.1.0.dist-info/entry_points.txt
Bullseye_DC-0.1.0.dist-info/top_level.txt
Bullseye_DC-0.1.0.dist-info/RECORD
