Metadata-Version: 2.1
Name: Bullseye-DC
Version: 0.1.0
Summary: A free program for performing tasks with Discord.
Author: purebluen73
Author-email: purebluen73@gmail.com
License: GNU General Public License v3 or later (GPLv3+)
Keywords: discord
Classifier: Development Status :: 4 - Beta
Classifier: Topic :: Internet
Classifier: License :: OSI Approved :: GNU General Public License v3 or later (GPLv3+)
Classifier: Operating System :: OS Independent
Classifier: Programming Language :: Python :: 3
Classifier: Programming Language :: Python :: 3.5
Classifier: Programming Language :: Python :: 3.6
Classifier: Programming Language :: Python :: 3.7
Requires-Python: >=3.5
License-File: LICENSE
Requires-Dist: Pillow >=4.1.1
Requires-Dist: requests <3,>=2.18.1
Requires-Dist: librecaptcha[gtk] <1,>=0.6.3
Requires-Dist: keyring >=17.0.0
